python_can_csscan_serial/CSSCANSerial.py
python_can_csscan_serial/__init__.py
python_can_csscan_serial-2.4.1.dist-info/METADATA
python_can_csscan_serial-2.4.1.dist-info/WHEEL
python_can_csscan_serial-2.4.1.dist-info/entry_points.txt
python_can_csscan_serial-2.4.1.dist-info/licenses/LICENSE
python_can_csscan_serial-2.4.1.dist-info/RECORD
